[{"source_file":"conference-17-resolutions-en","source_title":"17th OIML Conference — Resolutions (EN)","meeting_date":"2025-10-14","venue":"Paris, France","city":"Paris","country_code":"FR","year":"2025","body_type":"conference","language":"en","doi":"10.63493/meetings/conf17","resolution_count":11,"urn":"","virtual":false,"committee":"","localizations":[],"minutes":[]},{"source_file":"ciml-60-resolutions-en","source_title":"60th CIML Meeting — Resolutions (EN)","meeting_date":"2025-10-13","venue":"Paris, France","city":"Paris","country_code":"FR","year":"2025","body_type":"ciml","language":"en","doi":"10.63493/meetings/ciml60","resolution_count":44,"urn":"","virtual":false,"committee":"","localizations":[],"minutes":[]},{"source_file":"ciml-59-resolutions-en","source_title":"59th CIML Meeting — Resolutions (EN)","meeting_date":"2024-10-22","venue":"Online meeting","city":"","country_code":"","year":"2024","body_type":"ciml","language":"en","doi":"10.63493/meetings/ciml59","resolution_count":36,"urn":"","virtual":false,"committee":"","localizations":[],"minutes":[]},{"source_file":"ciml-58-resolutions-en","source_title":"58th CIML Meeting — Resolutions (EN)","meeting_date":"2023-10-17","venue":"Chiang Mai, Thailand","city":"Chiang Mai","country_code":"TH","year":"2023","body_type":"ciml","language":"en","doi":"10.63493/meetings/ciml58","resolution_count":37,"urn":"","virtual":false,"committee":"","localizations":[],"minutes":[]},{"source_file":"ciml-58-resolutions-fr","source_title":"58e réunion du CIML — Résolutions (FR)","meeting_date":"2023-10-17","venue":"Chiang Mai, Thailand","city":"Chiang Mai","country_code":"TH","year":"2023","body_type":"ciml","language":"fr","doi":"10.63493/meetings/ciml58","resolution_count":37,"urn":"","virtual":false,"committee":"","localizations":[],"minutes":[]},{"source_file":"ciml-57-resolutions-en","source_title":"57th CIML Meeting — Resolutions (EN)","meeting_date":"2022-10-18","venue":"Online meeting","city":"","country_code":"","year":"2022","body_type":"ciml","language":"en","doi":"10.63493/meetings/ciml57","resolution_count":48,"urn":"","virtual":false,"committee":"","localizations":[],"minutes":[]},{"source_file":"ciml-57-resolutions-fr","source_title":"57e réunion du CIML — Résolutions (FR)","meeting_date":"2022-10-18","venue":"Online meeting","city":"","country_code":"","year":"2022","body_type":"ciml","language":"fr","doi":"10.63493/meetings/ciml57","resolution_count":48,"urn":"","virtual":false,"committee":"","localizations":[],"minutes":[]},{"source_file":"ciml-56-resolutions-fr","source_title":"56e réunion du CIML — Résolutions (FR)","meeting_date":"2021-10-22","venue":"Online meeting","city":"","country_code":"","year":"2021","body_type":"ciml","language":"fr","doi":"10.63493/meetings/ciml56","resolution_count":41,"urn":"","virtual":false,"committee":"","localizations":[],"minutes":[]},{"source_file":"conference-16-resolutions-en","source_title":"16th OIML Conference — Resolutions (EN)","meeting_date":"2021-10-20","venue":"Online meeting","city":"","country_code":"","year":"2021","body_type":"conference","language":"en","doi":"10.63493/meetings/conf16","resolution_count":11,"urn":"","virtual":false,"committee":"","localizations":[],"minutes":[]},{"source_file":"conference-16-resolutions-fr","source_title":"16e Conférence OIML — Résolutions (FR)","meeting_date":"2021-10-20","venue":"Online meeting","city":"","country_code":"","year":"2021","body_type":"conference","language":"fr","doi":"10.63493/meetings/conf16","resolution_count":7,"urn":"","virtual":false,"committee":"","localizations":[],"minutes":[]},{"source_file":"ciml-56-resolutions-en","source_title":"56th CIML Meeting — Resolutions (EN)","meeting_date":"2021-10-19","venue":"Online meeting","city":"","country_code":"","year":"2021","body_type":"ciml","language":"en","doi":"10.63493/meetings/ciml56","resolution_count":41,"urn":"","virtual":false,"committee":"","localizations":[],"minutes":[]},{"source_file":"ciml-55-resolutions-en","source_title":"55th CIML Meeting — Resolutions (EN)","meeting_date":"2020-10-20","venue":"Online meeting","city":"","country_code":"","year":"2020","body_type":"ciml","language":"en","doi":"10.63493/meetings/ciml55","resolution_count":33,"urn":"","virtual":false,"committee":"","localizations":[],"minutes":[]},{"source_file":"ciml-55-resolutions-fr","source_title":"55e réunion du CIML — Résolutions (FR)","meeting_date":"2020-10-20","venue":"Online meeting","city":"","country_code":"","year":"2020","body_type":"ciml","language":"fr","doi":"10.63493/meetings/ciml55","resolution_count":33,"urn":"","virtual":false,"committee":"","localizations":[],"minutes":[]},{"source_file":"ciml-54-resolutions-en","source_title":"54th CIML Meeting — Resolutions (EN)","meeting_date":"2019-10-22","venue":"Bratislava, Slovak Republic","city":"Bratislava","country_code":"SK","year":"2019","body_type":"ciml","language":"en","doi":"10.63493/meetings/ciml54","resolution_count":37,"urn":"","virtual":false,"committee":"","localizations":[],"minutes":[]},{"source_file":"ciml-54-resolutions-fr","source_title":"54e réunion du CIML — Résolutions (FR)","meeting_date":"2019-10-22","venue":"Bratislava, Slovak Republic","city":"Bratislava","country_code":"SK","year":"2019","body_type":"ciml","language":"fr","doi":"10.63493/meetings/ciml54","resolution_count":37,"urn":"","virtual":false,"committee":"","localizations":[],"minutes":[]},{"source_file":"ciml-53-resolutions-en","source_title":"53rd CIML Meeting — Resolutions (EN)","meeting_date":"2018-10-09","venue":"Hamburg, Germany","city":"Hamburg","country_code":"DE","year":"2018","body_type":"ciml","language":"en","doi":"10.63493/meetings/ciml53","resolution_count":41,"urn":"","virtual":false,"committee":"","localizations":[],"minutes":[]},{"source_file":"ciml-53-resolutions-fr","source_title":"53e réunion du CIML — Résolutions (FR)","meeting_date":"2018-10-09","venue":"Hamburg, Germany","city":"Hamburg","country_code":"DE","year":"2018","body_type":"ciml","language":"fr","doi":"10.63493/meetings/ciml53","resolution_count":41,"urn":"","virtual":false,"committee":"","localizations":[],"minutes":[]},{"source_file":"ciml-52-resolutions-en","source_title":"52nd CIML Meeting — Resolutions (EN)","meeting_date":"2017-10-10","venue":"Cartagena de Indias, Colombia","city":"Cartagena de Indias","country_code":"CO","year":"2017","body_type":"ciml","language":"en","doi":"10.63493/meetings/ciml52","resolution_count":36,"urn":"","virtual":false,"committee":"","localizations":[],"minutes":[]},{"source_file":"ciml-52-resolutions-fr","source_title":"52e réunion du CIML — Résolutions (FR)","meeting_date":"2017-10-10","venue":"Cartagena de Indias, Colombia","city":"Cartagena de Indias","country_code":"CO","year":"2017","body_type":"ciml","language":"fr","doi":"10.63493/meetings/ciml52","resolution_count":36,"urn":"","virtual":false,"committee":"","localizations":[],"minutes":[]},{"source_file":"conference-15-resolutions-en","source_title":"15th OIML Conference — Resolutions (EN)","meeting_date":"2016-10-19","venue":"Strasbourg, France","city":"Strasbourg","country_code":"FR","year":"2016","body_type":"conference","language":"en","doi":"10.63493/meetings/conf15","resolution_count":8,"urn":"","virtual":false,"committee":"","localizations":[],"minutes":[]},{"source_file":"conference-15-resolutions-fr","source_title":"15e Conférence OIML — Résolutions (FR)","meeting_date":"2016-10-19","venue":"Strasbourg, France","city":"Strasbourg","country_code":"FR","year":"2016","body_type":"conference","language":"fr","doi":"10.63493/meetings/conf15","resolution_count":8,"urn":"","virtual":false,"committee":"","localizations":[],"minutes":[]},{"source_file":"ciml-51-resolutions-en","source_title":"51st CIML Meeting — Resolutions (EN)","meeting_date":"2016-10-17","venue":"Strasbourg, France","city":"Strasbourg","country_code":"FR","year":"2016","body_type":"ciml","language":"en","doi":"10.63493/meetings/ciml51","resolution_count":36,"urn":"","virtual":false,"committee":"","localizations":[],"minutes":[]},{"source_file":"ciml-51-resolutions-fr","source_title":"51e réunion du CIML — Résolutions (FR)","meeting_date":"2016-10-17","venue":"Strasbourg, France","city":"Strasbourg","country_code":"FR","year":"2016","body_type":"ciml","language":"fr","doi":"10.63493/meetings/ciml51","resolution_count":36,"urn":"","virtual":false,"committee":"","localizations":[],"minutes":[]},{"source_file":"ciml-50-resolutions-en","source_title":"50th CIML Meeting — Resolutions (EN)","meeting_date":"2015-10-20","venue":"Arcachon, France","city":"Arcachon","country_code":"FR","year":"2015","body_type":"ciml","language":"en","doi":"10.63493/meetings/ciml50","resolution_count":20,"urn":"","virtual":false,"committee":"","localizations":[],"minutes":[]},{"source_file":"ciml-50-resolutions-fr","source_title":"50e réunion du CIML — Résolutions (FR)","meeting_date":"2015-10-20","venue":"Arcachon, France","city":"Arcachon","country_code":"FR","year":"2015","body_type":"ciml","language":"fr","doi":"10.63493/meetings/ciml50","resolution_count":20,"urn":"","virtual":false,"committee":"","localizations":[],"minutes":[]},{"source_file":"ciml-49-resolutions-en","source_title":"49th CIML Meeting — Resolutions (EN)","meeting_date":"2014-11-04","venue":"Auckland, New Zealand","city":"Auckland","country_code":"NZ","year":"2014","body_type":"ciml","language":"en","doi":"10.63493/meetings/ciml49","resolution_count":20,"urn":"","virtual":false,"committee":"","localizations":[],"minutes":[]},{"source_file":"ciml-49-resolutions-fr","source_title":"49e réunion du CIML — Résolutions (FR)","meeting_date":"2014-11-04","venue":"Auckland, New Zealand","city":"Auckland","country_code":"NZ","year":"2014","body_type":"ciml","language":"fr","doi":"10.63493/meetings/ciml49","resolution_count":20,"urn":"","virtual":false,"committee":"","localizations":[],"minutes":[]},{"source_file":"ciml-48-resolutions-en","source_title":"48th CIML Meeting — Resolutions (EN)","meeting_date":"2013-10-08","venue":"Ho Chi Minh City, Viet Nam","city":"Ho Chi Minh City","country_code":"VN","year":"2013","body_type":"ciml","language":"en","doi":"10.63493/meetings/ciml48","resolution_count":20,"urn":"","virtual":false,"committee":"","localizations":[],"minutes":[]},{"source_file":"ciml-48-resolutions-fr","source_title":"48e réunion du CIML — Résolutions (FR)","meeting_date":"2013-10-08","venue":"Ho Chi Minh City, Viet Nam","city":"Ho Chi Minh City","country_code":"VN","year":"2013","body_type":"ciml","language":"fr","doi":"10.63493/meetings/ciml48","resolution_count":20,"urn":"","virtual":false,"committee":"","localizations":[],"minutes":[]},{"source_file":"conference-14-resolutions-en","source_title":"14th OIML Conference — Resolutions (EN)","meeting_date":"2012-10-03","venue":"Bucharest, Romania","city":"Bucharest","country_code":"RO","year":"2012","body_type":"conference","language":"en","doi":"10.63493/meetings/conf14","resolution_count":16,"urn":"","virtual":false,"committee":"","localizations":[],"minutes":[]},{"source_file":"conference-14-resolutions-fr","source_title":"14e Conférence OIML — Résolutions (FR)","meeting_date":"2012-10-03","venue":"Bucharest, Romania","city":"Bucharest","country_code":"RO","year":"2012","body_type":"conference","language":"fr","doi":"10.63493/meetings/conf14","resolution_count":16,"urn":"","virtual":false,"committee":"","localizations":[],"minutes":[]},{"source_file":"ciml-47-resolutions-en","source_title":"47th CIML Meeting — Resolutions (EN)","meeting_date":"2012-10-01","venue":"Bucharest, Romania","city":"Bucharest","country_code":"RO","year":"2012","body_type":"ciml","language":"en","doi":"10.63493/meetings/ciml47","resolution_count":26,"urn":"","virtual":false,"committee":"","localizations":[],"minutes":[]},{"source_file":"ciml-47-resolutions-fr","source_title":"47e réunion du CIML — Résolutions (FR)","meeting_date":"2012-10-01","venue":"Bucharest, Romania","city":"Bucharest","country_code":"RO","year":"2012","body_type":"ciml","language":"fr","doi":"10.63493/meetings/ciml47","resolution_count":26,"urn":"","virtual":false,"committee":"","localizations":[],"minutes":[]},{"source_file":"ciml-46-resolutions-en","source_title":"46th CIML Meeting — Resolutions (EN)","meeting_date":"2011-10-11","venue":"Prague, Czech Republic","city":"Prague","country_code":"CZ","year":"2011","body_type":"ciml","language":"en","doi":"10.63493/meetings/ciml46","resolution_count":31,"urn":"","virtual":false,"committee":"","localizations":[],"minutes":[]},{"source_file":"ciml-46-resolutions-fr","source_title":"46e réunion du CIML — Résolutions (FR)","meeting_date":"2011-10-11","venue":"Prague, Czech Republic","city":"Prague","country_code":"CZ","year":"2011","body_type":"ciml","language":"fr","doi":"10.63493/meetings/ciml46","resolution_count":31,"urn":"","virtual":false,"committee":"","localizations":[],"minutes":[]},{"source_file":"ciml-45-resolutions-en","source_title":"45th CIML Meeting — Resolutions (EN)","meeting_date":"2010-09-21","venue":"Orlando, USA","city":"Orlando","country_code":"US","year":"2010","body_type":"ciml","language":"en","doi":"10.63493/meetings/ciml45","resolution_count":35,"urn":"","virtual":false,"committee":"","localizations":[],"minutes":[]},{"source_file":"ciml-45-resolutions-fr","source_title":"45e réunion du CIML — Résolutions (FR)","meeting_date":"2010-09-21","venue":"Orlando, USA","city":"Orlando","country_code":"US","year":"2010","body_type":"ciml","language":"fr","doi":"10.63493/meetings/ciml45","resolution_count":35,"urn":"","virtual":false,"committee":"","localizations":[],"minutes":[]},{"source_file":"ciml-44-resolutions-en","source_title":"44th CIML Meeting — Resolutions (EN)","meeting_date":"2009-10-27","venue":"Mombasa, Kenya","city":"Mombasa","country_code":"KE","year":"2009","body_type":"ciml","language":"en","doi":"10.63493/meetings/ciml44","resolution_count":27,"urn":"","virtual":false,"committee":"","localizations":[],"minutes":[]},{"source_file":"ciml-44-resolutions-fr","source_title":"44e réunion du CIML — Résolutions (FR)","meeting_date":"2009-10-27","venue":"Mombasa, Kenya","city":"Mombasa","country_code":"KE","year":"2009","body_type":"ciml","language":"fr","doi":"10.63493/meetings/ciml44","resolution_count":27,"urn":"","virtual":false,"committee":"","localizations":[],"minutes":[]},{"source_file":"conference-13-resolutions-bilingual-en","source_title":"Resolutions of the 13th OIML Conference (2008)","meeting_date":"2008-10-29","venue":"Sydney, Australia","city":"Sydney","country_code":"AU","year":"2008","body_type":"conference","language":"en","doi":"10.63493/meetings/conf13","resolution_count":6,"urn":"","virtual":false,"committee":"","localizations":[],"minutes":[]},{"source_file":"conference-13-resolutions-bilingual-fr","source_title":"Résolutions 13e OIML Conference (2008)","meeting_date":"2008-10-29","venue":"Sydney, Australia","city":"Sydney","country_code":"AU","year":"2008","body_type":"conference","language":"fr","doi":"10.63493/meetings/conf13","resolution_count":38,"urn":"","virtual":false,"committee":"","localizations":[],"minutes":[]},{"source_file":"ciml-43-resolutions-bilingual-en","source_title":"Resolutions of the 43rd CIML Meeting (2008)","meeting_date":"2008-10-28","venue":"Sydney, Australia","city":"Sydney","country_code":"AU","year":"2008","body_type":"ciml","language":"en","doi":"10.63493/meetings/ciml43","resolution_count":6,"urn":"","virtual":false,"committee":"","localizations":[],"minutes":[]},{"source_file":"ciml-43-resolutions-bilingual-fr","source_title":"Résolutions 43e CIML Meeting (2008)","meeting_date":"2008-10-28","venue":"Sydney, Australia","city":"Sydney","country_code":"AU","year":"2008","body_type":"ciml","language":"fr","doi":"10.63493/meetings/ciml43","resolution_count":58,"urn":"","virtual":false,"committee":"","localizations":[],"minutes":[]},{"source_file":"ciml-42-decisions-en","source_title":"42nd CIML Meeting — Decisions (EN)","meeting_date":"2007-10-24","venue":"Shanghai, P.R. China","city":"Shanghai","country_code":"CN","year":"2007","body_type":"ciml","language":"en","doi":"10.63493/meetings/ciml42","resolution_count":36,"urn":"","virtual":false,"committee":"","localizations":[],"minutes":[]},{"source_file":"ciml-42-decisions-fr","source_title":"42e réunion du CIML — Décisions (FR)","meeting_date":"2007-10-24","venue":"Shanghai, P.R. China","city":"Shanghai","country_code":"CN","year":"2007","body_type":"ciml","language":"fr","doi":"10.63493/meetings/ciml42","resolution_count":35,"urn":"","virtual":false,"committee":"","localizations":[],"minutes":[]},{"source_file":"ciml-41-decisions-en","source_title":"41st CIML Meeting — Decisions (EN)","meeting_date":"2006-10-18","venue":"Cape Town, South Africa","city":"Cape Town","country_code":"ZA","year":"2006","body_type":"ciml","language":"en","doi":"10.63493/meetings/ciml41","resolution_count":38,"urn":"","virtual":false,"committee":"","localizations":[],"minutes":[]},{"source_file":"ciml-41-decisions-fr","source_title":"41e réunion du CIML — Décisions (FR)","meeting_date":"2006-10-18","venue":"Cape Town, South Africa","city":"Cape Town","country_code":"ZA","year":"2006","body_type":"ciml","language":"fr","doi":"10.63493/meetings/ciml41","resolution_count":38,"urn":"","virtual":false,"committee":"","localizations":[],"minutes":[]},{"source_file":"ciml-40-decisions-en","source_title":"40th CIML Meeting — Decisions (EN)","meeting_date":"2005-06-18","venue":"Lyon, France","city":"Lyon","country_code":"FR","year":"2005","body_type":"ciml","language":"en","doi":"10.63493/meetings/ciml40","resolution_count":31,"urn":"","virtual":false,"committee":"","localizations":[],"minutes":[]},{"source_file":"ciml-40-decisions-fr","source_title":"40e réunion du CIML — Décisions (FR)","meeting_date":"2005-06-18","venue":"Lyon, France","city":"Lyon","country_code":"FR","year":"2005","body_type":"ciml","language":"fr","doi":"10.63493/meetings/ciml40","resolution_count":32,"urn":"","virtual":false,"committee":"","localizations":[],"minutes":[]},{"source_file":"ciml-39-decisions-en","source_title":"39th CIML Meeting — Decisions (EN)","meeting_date":"2004-10-26","venue":"Berlin, Germany","city":"Berlin","country_code":"DE","year":"2004","body_type":"ciml","language":"en","doi":"10.63493/meetings/ciml39","resolution_count":24,"urn":"","virtual":false,"committee":"","localizations":[],"minutes":[]},{"source_file":"ciml-39-decisions-fr","source_title":"39e réunion du CIML — Décisions (FR)","meeting_date":"2004-10-26","venue":"Berlin, Germany","city":"Berlin","country_code":"DE","year":"2004","body_type":"ciml","language":"fr","doi":"10.63493/meetings/ciml39","resolution_count":23,"urn":"","virtual":false,"committee":"","localizations":[],"minutes":[]},{"source_file":"conference-12-decisions-en","source_title":"12th OIML Conference — Joint CIML-39 + DC Decisions (EN)","meeting_date":"2004-10-26","venue":"Berlin, Germany","city":"Berlin","country_code":"DE","year":"2004","body_type":"conference","language":"en","doi":"10.63493/meetings/conf12","resolution_count":109,"urn":"","virtual":false,"committee":"","localizations":[],"minutes":[]},{"source_file":"conference-12-decisions-fr","source_title":"12e Conférence OIML — Décisions (FR)","meeting_date":"2004-10-26","venue":"Berlin, Germany","city":"Berlin","country_code":"DE","year":"2004","body_type":"conference","language":"fr","doi":"10.63493/meetings/conf12","resolution_count":33,"urn":"","virtual":false,"committee":"","localizations":[],"minutes":[]},{"source_file":"ciml-10-resolutions","source_title":"10th CIML Meeting (skeleton from minutes)","meeting_date":"","venue":"","city":"","country_code":"","year":"","body_type":"ciml","language":"fr","doi":"","resolution_count":0,"urn":"urn:oiml:ciml:meeting:ciml-10","virtual":false,"committee":"","localizations":[{"language_code":"fra","script":"Latn","title":"10th CIML Meeting (skeleton from minutes)","general_area":""}],"minutes":[{"urn":"urn:oiml:ciml:minutes:ciml-10-fra","language_code":"fra"}]},{"source_file":"ciml-15-resolutions","source_title":"15th CIML Meeting (skeleton from minutes)","meeting_date":"","venue":"","city":"","country_code":"","year":"","body_type":"ciml","language":"fr","doi":"","resolution_count":0,"urn":"urn:oiml:ciml:meeting:ciml-15","virtual":false,"committee":"","localizations":[{"language_code":"fra","script":"Latn","title":"15th CIML Meeting (skeleton from minutes)","general_area":""}],"minutes":[{"urn":"urn:oiml:ciml:minutes:ciml-15-fra","language_code":"fra"}]},{"source_file":"ciml-16-resolutions","source_title":"16th CIML Meeting (skeleton from minutes)","meeting_date":"","venue":"","city":"","country_code":"","year":"","body_type":"ciml","language":"fr","doi":"","resolution_count":0,"urn":"urn:oiml:ciml:meeting:ciml-16","virtual":false,"committee":"","localizations":[{"language_code":"fra","script":"Latn","title":"16th CIML Meeting (skeleton from minutes)","general_area":""}],"minutes":[{"urn":"urn:oiml:ciml:minutes:ciml-16-fra","language_code":"fra"}]},{"source_file":"ciml-17-resolutions","source_title":"17th CIML Meeting (skeleton from minutes)","meeting_date":"","venue":"","city":"","country_code":"","year":"","body_type":"ciml","language":"en","doi":"","resolution_count":0,"urn":"urn:oiml:ciml:meeting:ciml-17","virtual":false,"committee":"","localizations":[{"language_code":"eng","script":"Latn","title":"17th CIML Meeting (skeleton from minutes)","general_area":""}],"minutes":[{"urn":"urn:oiml:ciml:minutes:ciml-17-eng","language_code":"eng"}]},{"source_file":"ciml-18-resolutions","source_title":"18th CIML Meeting (skeleton from minutes)","meeting_date":"","venue":"","city":"","country_code":"","year":"","body_type":"ciml","language":"fr","doi":"","resolution_count":0,"urn":"urn:oiml:ciml:meeting:ciml-18","virtual":false,"committee":"","localizations":[{"language_code":"fra","script":"Latn","title":"18th CIML Meeting (skeleton from minutes)","general_area":""}],"minutes":[{"urn":"urn:oiml:ciml:minutes:ciml-18-fra","language_code":"fra"}]},{"source_file":"ciml-19-resolutions","source_title":"19th CIML Meeting (skeleton from minutes)","meeting_date":"","venue":"","city":"","country_code":"","year":"","body_type":"ciml","language":"fr","doi":"","resolution_count":0,"urn":"urn:oiml:ciml:meeting:ciml-19","virtual":false,"committee":"","localizations":[{"language_code":"fra","script":"Latn","title":"19th CIML Meeting (skeleton from minutes)","general_area":""}],"minutes":[{"urn":"urn:oiml:ciml:minutes:ciml-19-fra","language_code":"fra"}]},{"source_file":"ciml-20-resolutions","source_title":"20th CIML Meeting (skeleton from minutes)","meeting_date":"","venue":"","city":"","country_code":"","year":"","body_type":"ciml","language":"en","doi":"","resolution_count":0,"urn":"urn:oiml:ciml:meeting:ciml-20","virtual":false,"committee":"","localizations":[{"language_code":"eng","script":"Latn","title":"20th CIML Meeting (skeleton from minutes)","general_area":""}],"minutes":[{"urn":"urn:oiml:ciml:minutes:ciml-20-eng","language_code":"eng"}]},{"source_file":"ciml-21-resolutions","source_title":"21th CIML Meeting (skeleton from minutes)","meeting_date":"","venue":"","city":"","country_code":"","year":"","body_type":"ciml","language":"en","doi":"","resolution_count":0,"urn":"urn:oiml:ciml:meeting:ciml-21","virtual":false,"committee":"","localizations":[{"language_code":"eng","script":"Latn","title":"21th CIML Meeting (skeleton from minutes)","general_area":""}],"minutes":[{"urn":"urn:oiml:ciml:minutes:ciml-21-eng","language_code":"eng"}]},{"source_file":"ciml-22-resolutions","source_title":"22th CIML Meeting (skeleton from minutes)","meeting_date":"","venue":"","city":"","country_code":"","year":"","body_type":"ciml","language":"en","doi":"","resolution_count":0,"urn":"urn:oiml:ciml:meeting:ciml-22","virtual":false,"committee":"","localizations":[{"language_code":"eng","script":"Latn","title":"22th CIML Meeting (skeleton from minutes)","general_area":""}],"minutes":[{"urn":"urn:oiml:ciml:minutes:ciml-22-eng","language_code":"eng"}]},{"source_file":"ciml-23-resolutions","source_title":"23th CIML Meeting (skeleton from minutes)","meeting_date":"","venue":"","city":"","country_code":"","year":"","body_type":"ciml","language":"en","doi":"","resolution_count":0,"urn":"urn:oiml:ciml:meeting:ciml-23","virtual":false,"committee":"","localizations":[{"language_code":"eng","script":"Latn","title":"23th CIML Meeting (skeleton from minutes)","general_area":""}],"minutes":[{"urn":"urn:oiml:ciml:minutes:ciml-23-eng","language_code":"eng"}]},{"source_file":"ciml-25-resolutions","source_title":"25th CIML Meeting (skeleton from minutes)","meeting_date":"","venue":"","city":"","country_code":"","year":"","body_type":"ciml","language":"en","doi":"","resolution_count":0,"urn":"urn:oiml:ciml:meeting:ciml-25","virtual":false,"committee":"","localizations":[{"language_code":"eng","script":"Latn","title":"25th CIML Meeting (skeleton from minutes)","general_area":""}],"minutes":[{"urn":"urn:oiml:ciml:minutes:ciml-25-eng","language_code":"eng"}]},{"source_file":"ciml-26-resolutions","source_title":"26th CIML Meeting (skeleton from minutes)","meeting_date":"","venue":"","city":"","country_code":"","year":"","body_type":"ciml","language":"en","doi":"","resolution_count":0,"urn":"urn:oiml:ciml:meeting:ciml-26","virtual":false,"committee":"","localizations":[{"language_code":"eng","script":"Latn","title":"26th CIML Meeting (skeleton from minutes)","general_area":""}],"minutes":[{"urn":"urn:oiml:ciml:minutes:ciml-26-eng","language_code":"eng"}]},{"source_file":"ciml-27-resolutions","source_title":"27th CIML Meeting (skeleton from minutes)","meeting_date":"","venue":"","city":"","country_code":"","year":"","body_type":"ciml","language":"fr","doi":"","resolution_count":0,"urn":"urn:oiml:ciml:meeting:ciml-27","virtual":false,"committee":"","localizations":[{"language_code":"fra","script":"Latn","title":"27th CIML Meeting (skeleton from minutes)","general_area":""}],"minutes":[{"urn":"urn:oiml:ciml:minutes:ciml-27-fra","language_code":"fra"}]},{"source_file":"ciml-28-resolutions","source_title":"28th CIML Meeting (skeleton from minutes)","meeting_date":"","venue":"","city":"","country_code":"","year":"","body_type":"ciml","language":"fr","doi":"","resolution_count":0,"urn":"urn:oiml:ciml:meeting:ciml-28","virtual":false,"committee":"","localizations":[{"language_code":"fra","script":"Latn","title":"28th CIML Meeting (skeleton from minutes)","general_area":""}],"minutes":[{"urn":"urn:oiml:ciml:minutes:ciml-28-fra","language_code":"fra"}]},{"source_file":"ciml-32-resolutions","source_title":"32th CIML Meeting (skeleton from minutes)","meeting_date":"","venue":"","city":"","country_code":"","year":"","body_type":"ciml","language":"en","doi":"","resolution_count":0,"urn":"urn:oiml:ciml:meeting:ciml-32","virtual":false,"committee":"","localizations":[{"language_code":"eng","script":"Latn","title":"32th CIML Meeting (skeleton from minutes)","general_area":""}],"minutes":[{"urn":"urn:oiml:ciml:minutes:ciml-32-eng","language_code":"eng"}]},{"source_file":"ciml-33-resolutions","source_title":"33th CIML Meeting (skeleton from minutes)","meeting_date":"","venue":"","city":"","country_code":"","year":"","body_type":"ciml","language":"fr","doi":"","resolution_count":0,"urn":"urn:oiml:ciml:meeting:ciml-33","virtual":false,"committee":"","localizations":[{"language_code":"fra","script":"Latn","title":"33th CIML Meeting (skeleton from minutes)","general_area":""}],"minutes":[{"urn":"urn:oiml:ciml:minutes:ciml-33-fra","language_code":"fra"}]},{"source_file":"ciml-34-resolutions","source_title":"34th CIML Meeting (skeleton from minutes)","meeting_date":"","venue":"","city":"","country_code":"","year":"","body_type":"ciml","language":"fr","doi":"","resolution_count":0,"urn":"urn:oiml:ciml:meeting:ciml-34","virtual":false,"committee":"","localizations":[{"language_code":"fra","script":"Latn","title":"34th CIML Meeting (skeleton from minutes)","general_area":""}],"minutes":[{"urn":"urn:oiml:ciml:minutes:ciml-34-fra","language_code":"fra"}]},{"source_file":"ciml-35-resolutions","source_title":"35th CIML Meeting (skeleton from minutes)","meeting_date":"","venue":"","city":"","country_code":"","year":"","body_type":"ciml","language":"fr","doi":"","resolution_count":0,"urn":"urn:oiml:ciml:meeting:ciml-35","virtual":false,"committee":"","localizations":[{"language_code":"fra","script":"Latn","title":"35th CIML Meeting (skeleton from minutes)","general_area":""}],"minutes":[{"urn":"urn:oiml:ciml:minutes:ciml-35-fra","language_code":"fra"}]},{"source_file":"ciml-36-resolutions","source_title":"36th CIML Meeting (skeleton from minutes)","meeting_date":"","venue":"","city":"","country_code":"","year":"","body_type":"ciml","language":"fr","doi":"","resolution_count":0,"urn":"urn:oiml:ciml:meeting:ciml-36","virtual":false,"committee":"","localizations":[{"language_code":"fra","script":"Latn","title":"36th CIML Meeting (skeleton from minutes)","general_area":""}],"minutes":[{"urn":"urn:oiml:ciml:minutes:ciml-36-fra","language_code":"fra"}]},{"source_file":"ciml-37-resolutions","source_title":"37th CIML Meeting (skeleton from minutes)","meeting_date":"","venue":"","city":"","country_code":"","year":"","body_type":"ciml","language":"fr","doi":"","resolution_count":0,"urn":"urn:oiml:ciml:meeting:ciml-37","virtual":false,"committee":"","localizations":[{"language_code":"fra","script":"Latn","title":"37th CIML Meeting (skeleton from minutes)","general_area":""}],"minutes":[{"urn":"urn:oiml:ciml:minutes:ciml-37-fra","language_code":"fra"}]},{"source_file":"ciml-38-resolutions","source_title":"38th CIML Meeting (skeleton from minutes)","meeting_date":"","venue":"","city":"","country_code":"","year":"","body_type":"ciml","language":"en","doi":"","resolution_count":0,"urn":"urn:oiml:ciml:meeting:ciml-38","virtual":false,"committee":"","localizations":[{"language_code":"eng","script":"Latn","title":"38th CIML Meeting (skeleton from minutes)","general_area":""},{"language_code":"fra","script":"Latn","title":"38th CIML Meeting (skeleton from minutes)","general_area":""}],"minutes":[{"urn":"urn:oiml:ciml:minutes:ciml-38-eng","language_code":"eng"},{"urn":"urn:oiml:ciml:minutes:ciml-38-fra","language_code":"fra"}]},{"source_file":"ciml-39-resolutions","source_title":"39th CIML Meeting — Decisions (EN)","meeting_date":"","venue":"Berlin, Germany","city":"","country_code":"","year":"","body_type":"ciml","language":"en","doi":"","resolution_count":0,"urn":"urn:oiml:ciml:meeting:ciml-39","virtual":false,"committee":"International Committee of Legal Metrology (CIML)","localizations":[{"language_code":"eng","script":"Latn","title":"39th CIML Meeting — Decisions (EN)","general_area":"Berlin, Germany"},{"language_code":"fra","script":"Latn","title":"39e réunion du CIML — Décisions (FR)","general_area":"Berlin, Germany"}],"minutes":[{"urn":"urn:oiml:ciml:minutes:ciml-39-eng","language_code":"eng"}]},{"source_file":"ciml-4-resolutions","source_title":"4th CIML Meeting (skeleton from minutes)","meeting_date":"","venue":"","city":"","country_code":"","year":"","body_type":"ciml","language":"fr","doi":"","resolution_count":0,"urn":"urn:oiml:ciml:meeting:ciml-4","virtual":false,"committee":"","localizations":[{"language_code":"fra","script":"Latn","title":"4th CIML Meeting (skeleton from minutes)","general_area":""}],"minutes":[{"urn":"urn:oiml:ciml:minutes:ciml-4-fra","language_code":"fra"}]},{"source_file":"ciml-40-resolutions","source_title":"40th CIML Meeting — Decisions (EN)","meeting_date":"","venue":"Lyon, France","city":"","country_code":"","year":"","body_type":"ciml","language":"en","doi":"","resolution_count":0,"urn":"urn:oiml:ciml:meeting:ciml-40","virtual":false,"committee":"International Committee of Legal Metrology (CIML)","localizations":[{"language_code":"eng","script":"Latn","title":"40th CIML Meeting — Decisions (EN)","general_area":"Lyon, France"},{"language_code":"fra","script":"Latn","title":"40e réunion du CIML — Décisions (FR)","general_area":"Lyon, France"}],"minutes":[]},{"source_file":"ciml-41-resolutions","source_title":"41st CIML Meeting — Decisions (EN)","meeting_date":"","venue":"Cape Town, South Africa","city":"","country_code":"","year":"","body_type":"ciml","language":"en","doi":"","resolution_count":0,"urn":"urn:oiml:ciml:meeting:ciml-41","virtual":false,"committee":"International Committee of Legal Metrology (CIML)","localizations":[{"language_code":"eng","script":"Latn","title":"41st CIML Meeting — Decisions (EN)","general_area":"Cape Town, South Africa"},{"language_code":"fra","script":"Latn","title":"41e réunion du CIML — Décisions (FR)","general_area":"Cape Town, South Africa"}],"minutes":[{"urn":"urn:oiml:ciml:minutes:ciml-41-eng","language_code":"eng"}]},{"source_file":"ciml-42-resolutions","source_title":"42nd CIML Meeting — Decisions (EN)","meeting_date":"","venue":"Shanghai, P.R. China","city":"","country_code":"","year":"","body_type":"ciml","language":"en","doi":"","resolution_count":0,"urn":"urn:oiml:ciml:meeting:ciml-42","virtual":false,"committee":"International Committee of Legal Metrology (CIML)","localizations":[{"language_code":"eng","script":"Latn","title":"42nd CIML Meeting — Decisions (EN)","general_area":"Shanghai, P.R. China"},{"language_code":"fra","script":"Latn","title":"42e réunion du CIML — Décisions (FR)","general_area":"Shanghai, P.R. China"}],"minutes":[{"urn":"urn:oiml:ciml:minutes:ciml-42-eng","language_code":"eng"},{"urn":"urn:oiml:ciml:minutes:ciml-42-fra","language_code":"fra"}]},{"source_file":"ciml-43-resolutions","source_title":"43rd CIML Meeting — Resolutions (EN/FR)","meeting_date":"","venue":"Sydney, Australia","city":"","country_code":"","year":"","body_type":"ciml","language":"en","doi":"","resolution_count":0,"urn":"urn:oiml:ciml:meeting:ciml-43","virtual":false,"committee":"International Committee of Legal Metrology (CIML)","localizations":[{"language_code":"eng","script":"Latn","title":"43rd CIML Meeting — Resolutions (EN/FR)","general_area":"Sydney, Australia"},{"language_code":"fra","script":"Latn","title":"43rd CIML Meeting — Resolutions (EN/FR)","general_area":"Sydney, Australia"}],"minutes":[]},{"source_file":"ciml-44-resolutions","source_title":"44th CIML Meeting — Resolutions (EN)","meeting_date":"","venue":"Mombasa, Kenya","city":"","country_code":"","year":"","body_type":"ciml","language":"en","doi":"","resolution_count":0,"urn":"urn:oiml:ciml:meeting:ciml-44","virtual":false,"committee":"International Committee of Legal Metrology (CIML)","localizations":[{"language_code":"eng","script":"Latn","title":"44th CIML Meeting — Resolutions (EN)","general_area":"Mombasa, Kenya"},{"language_code":"fra","script":"Latn","title":"44e réunion du CIML — Résolutions (FR)","general_area":"Mombasa, Kenya"}],"minutes":[]},{"source_file":"ciml-45-resolutions","source_title":"45th CIML Meeting — Resolutions (EN)","meeting_date":"","venue":"Orlando, USA","city":"","country_code":"","year":"","body_type":"ciml","language":"en","doi":"","resolution_count":0,"urn":"urn:oiml:ciml:meeting:ciml-45","virtual":false,"committee":"International Committee of Legal Metrology (CIML)","localizations":[{"language_code":"eng","script":"Latn","title":"45th CIML Meeting — Resolutions (EN)","general_area":"Orlando, USA"},{"language_code":"fra","script":"Latn","title":"45e réunion du CIML — Résolutions (FR)","general_area":"Orlando, USA"}],"minutes":[]},{"source_file":"ciml-46-resolutions","source_title":"46th CIML Meeting — Resolutions (EN)","meeting_date":"","venue":"Prague, Czech Republic","city":"","country_code":"","year":"","body_type":"ciml","language":"en","doi":"","resolution_count":0,"urn":"urn:oiml:ciml:meeting:ciml-46","virtual":false,"committee":"International Committee of Legal Metrology (CIML)","localizations":[{"language_code":"eng","script":"Latn","title":"46th CIML Meeting — Resolutions (EN)","general_area":"Prague, Czech Republic"},{"language_code":"fra","script":"Latn","title":"46e réunion du CIML — Résolutions (FR)","general_area":"Prague, Czech Republic"}],"minutes":[]},{"source_file":"ciml-47-resolutions","source_title":"47th CIML Meeting — Resolutions (EN)","meeting_date":"","venue":"Bucharest, Romania","city":"","country_code":"","year":"","body_type":"ciml","language":"en","doi":"","resolution_count":0,"urn":"urn:oiml:ciml:meeting:ciml-47","virtual":false,"committee":"International Committee of Legal Metrology (CIML)","localizations":[{"language_code":"eng","script":"Latn","title":"47th CIML Meeting — Resolutions (EN)","general_area":"Bucharest, Romania"},{"language_code":"fra","script":"Latn","title":"47e réunion du CIML — Résolutions (FR)","general_area":"Bucharest, Romania"}],"minutes":[]},{"source_file":"ciml-48-resolutions","source_title":"48th CIML Meeting — Resolutions (EN)","meeting_date":"","venue":"Ho Chi Minh City, Viet Nam","city":"","country_code":"","year":"","body_type":"ciml","language":"en","doi":"","resolution_count":0,"urn":"urn:oiml:ciml:meeting:ciml-48","virtual":false,"committee":"International Committee of Legal Metrology (CIML)","localizations":[{"language_code":"eng","script":"Latn","title":"48th CIML Meeting — Resolutions (EN)","general_area":"Ho Chi Minh City, Viet Nam"},{"language_code":"fra","script":"Latn","title":"48e réunion du CIML — Résolutions (FR)","general_area":"Ho Chi Minh City, Viet Nam"}],"minutes":[{"urn":"urn:oiml:ciml:minutes:ciml-48-fra","language_code":"fra"}]},{"source_file":"ciml-49-resolutions","source_title":"49th CIML Meeting — Resolutions (EN)","meeting_date":"","venue":"Auckland, New Zealand","city":"","country_code":"","year":"","body_type":"ciml","language":"en","doi":"","resolution_count":0,"urn":"urn:oiml:ciml:meeting:ciml-49","virtual":false,"committee":"International Committee of Legal Metrology (CIML)","localizations":[{"language_code":"eng","script":"Latn","title":"49th CIML Meeting — Resolutions (EN)","general_area":"Auckland, New Zealand"},{"language_code":"fra","script":"Latn","title":"49e réunion du CIML — Résolutions (FR)","general_area":"Auckland, New Zealand"}],"minutes":[]},{"source_file":"ciml-50-resolutions","source_title":"50th CIML Meeting — Resolutions (EN)","meeting_date":"","venue":"Arcachon, France","city":"","country_code":"","year":"","body_type":"ciml","language":"en","doi":"","resolution_count":0,"urn":"urn:oiml:ciml:meeting:ciml-50","virtual":false,"committee":"International Committee of Legal Metrology (CIML)","localizations":[{"language_code":"eng","script":"Latn","title":"50th CIML Meeting — Resolutions (EN)","general_area":"Arcachon, France"},{"language_code":"fra","script":"Latn","title":"50e réunion du CIML — Résolutions (FR)","general_area":"Arcachon, France"}],"minutes":[]},{"source_file":"ciml-51-resolutions","source_title":"51st CIML Meeting — Resolutions (EN)","meeting_date":"","venue":"Strasbourg, France","city":"","country_code":"","year":"","body_type":"ciml","language":"en","doi":"","resolution_count":0,"urn":"urn:oiml:ciml:meeting:ciml-51","virtual":false,"committee":"International Committee of Legal Metrology (CIML)","localizations":[{"language_code":"eng","script":"Latn","title":"51st CIML Meeting — Resolutions (EN)","general_area":"Strasbourg, France"},{"language_code":"fra","script":"Latn","title":"51e réunion du CIML — Résolutions (FR)","general_area":"Strasbourg, France"}],"minutes":[]},{"source_file":"ciml-52-resolutions","source_title":"52nd CIML Meeting — Resolutions (EN)","meeting_date":"","venue":"Cartagena de Indias, Colombia","city":"","country_code":"","year":"","body_type":"ciml","language":"en","doi":"","resolution_count":0,"urn":"urn:oiml:ciml:meeting:ciml-52","virtual":false,"committee":"International Committee of Legal Metrology (CIML)","localizations":[{"language_code":"eng","script":"Latn","title":"52nd CIML Meeting — Resolutions (EN)","general_area":"Cartagena de Indias, Colombia"},{"language_code":"fra","script":"Latn","title":"52e réunion du CIML — Résolutions (FR)","general_area":"Cartagena de Indias, Colombia"}],"minutes":[]},{"source_file":"ciml-53-resolutions","source_title":"53rd CIML Meeting — Resolutions (EN)","meeting_date":"","venue":"Hamburg, Germany","city":"","country_code":"","year":"","body_type":"ciml","language":"en","doi":"","resolution_count":0,"urn":"urn:oiml:ciml:meeting:ciml-53","virtual":false,"committee":"International Committee of Legal Metrology (CIML)","localizations":[{"language_code":"eng","script":"Latn","title":"53rd CIML Meeting — Resolutions (EN)","general_area":"Hamburg, Germany"},{"language_code":"fra","script":"Latn","title":"53e réunion du CIML — Résolutions (FR)","general_area":"Hamburg, Germany"}],"minutes":[]},{"source_file":"ciml-54-resolutions","source_title":"54th CIML Meeting — Resolutions (EN)","meeting_date":"","venue":"Bratislava, Slovak Republic","city":"","country_code":"","year":"","body_type":"ciml","language":"en","doi":"","resolution_count":0,"urn":"urn:oiml:ciml:meeting:ciml-54","virtual":false,"committee":"International Committee of Legal Metrology (CIML)","localizations":[{"language_code":"eng","script":"Latn","title":"54th CIML Meeting — Resolutions (EN)","general_area":"Bratislava, Slovak Republic"},{"language_code":"fra","script":"Latn","title":"54e réunion du CIML — Résolutions (FR)","general_area":"Bratislava, Slovak Republic"}],"minutes":[]},{"source_file":"ciml-55-resolutions","source_title":"55th CIML Meeting — Resolutions (EN)","meeting_date":"","venue":"Online meeting","city":"","country_code":"","year":"","body_type":"ciml","language":"en","doi":"","resolution_count":0,"urn":"urn:oiml:ciml:meeting:ciml-55","virtual":true,"committee":"International Committee of Legal Metrology (CIML)","localizations":[{"language_code":"eng","script":"Latn","title":"55th CIML Meeting — Resolutions (EN)","general_area":"Online meeting"},{"language_code":"fra","script":"Latn","title":"55e réunion du CIML — Résolutions (FR)","general_area":"Online meeting"}],"minutes":[]},{"source_file":"ciml-56-resolutions","source_title":"56th CIML Meeting — Resolutions (EN)","meeting_date":"","venue":"Online meeting","city":"","country_code":"","year":"","body_type":"ciml","language":"en","doi":"","resolution_count":0,"urn":"urn:oiml:ciml:meeting:ciml-56","virtual":true,"committee":"International Committee of Legal Metrology (CIML)","localizations":[{"language_code":"eng","script":"Latn","title":"56th CIML Meeting — Resolutions (EN)","general_area":"Online meeting"},{"language_code":"fra","script":"Latn","title":"56e réunion du CIML — Résolutions (FR)","general_area":"Online meeting"}],"minutes":[]},{"source_file":"ciml-57-resolutions","source_title":"57th CIML Meeting — Resolutions (EN)","meeting_date":"","venue":"Online meeting","city":"","country_code":"","year":"","body_type":"ciml","language":"en","doi":"","resolution_count":0,"urn":"urn:oiml:ciml:meeting:ciml-57","virtual":true,"committee":"International Committee of Legal Metrology (CIML)","localizations":[{"language_code":"eng","script":"Latn","title":"57th CIML Meeting — Resolutions (EN)","general_area":"Online meeting"},{"language_code":"fra","script":"Latn","title":"57e réunion du CIML — Résolutions (FR)","general_area":"Online meeting"}],"minutes":[]},{"source_file":"ciml-58-resolutions","source_title":"58th CIML Meeting — Resolutions (EN)","meeting_date":"","venue":"Chiang Mai, Thailand","city":"","country_code":"","year":"","body_type":"ciml","language":"en","doi":"","resolution_count":0,"urn":"urn:oiml:ciml:meeting:ciml-58","virtual":false,"committee":"International Committee of Legal Metrology (CIML)","localizations":[{"language_code":"eng","script":"Latn","title":"58th CIML Meeting — Resolutions (EN)","general_area":"Chiang Mai, Thailand"},{"language_code":"fra","script":"Latn","title":"58e réunion du CIML — Résolutions (FR)","general_area":"Chiang Mai, Thailand"}],"minutes":[]},{"source_file":"ciml-59-resolutions","source_title":"59th CIML Meeting — Resolutions (EN)","meeting_date":"","venue":"Online meeting","city":"","country_code":"","year":"","body_type":"ciml","language":"en","doi":"","resolution_count":0,"urn":"urn:oiml:ciml:meeting:ciml-59","virtual":true,"committee":"International Committee of Legal Metrology (CIML)","localizations":[{"language_code":"eng","script":"Latn","title":"59th CIML Meeting — Resolutions (EN)","general_area":"Online meeting"}],"minutes":[]},{"source_file":"ciml-6-resolutions","source_title":"6th CIML Meeting (skeleton from minutes)","meeting_date":"","venue":"","city":"","country_code":"","year":"","body_type":"ciml","language":"fr","doi":"","resolution_count":0,"urn":"urn:oiml:ciml:meeting:ciml-6","virtual":false,"committee":"","localizations":[{"language_code":"fra","script":"Latn","title":"6th CIML Meeting (skeleton from minutes)","general_area":""}],"minutes":[{"urn":"urn:oiml:ciml:minutes:ciml-6-fra","language_code":"fra"}]},{"source_file":"ciml-60-resolutions","source_title":"60th CIML Meeting — Resolutions (EN)","meeting_date":"","venue":"Paris, France","city":"","country_code":"","year":"","body_type":"ciml","language":"en","doi":"","resolution_count":0,"urn":"urn:oiml:ciml:meeting:ciml-60","virtual":false,"committee":"International Committee of Legal Metrology (CIML)","localizations":[{"language_code":"eng","script":"Latn","title":"60th CIML Meeting — Resolutions (EN)","general_area":"Paris, France"}],"minutes":[{"urn":"urn:oiml:ciml:minutes:ciml-60-eng","language_code":"eng"}]},{"source_file":"ciml-7-resolutions","source_title":"7th CIML Meeting (skeleton from minutes)","meeting_date":"","venue":"","city":"","country_code":"","year":"","body_type":"ciml","language":"fr","doi":"","resolution_count":0,"urn":"urn:oiml:ciml:meeting:ciml-7","virtual":false,"committee":"","localizations":[{"language_code":"fra","script":"Latn","title":"7th CIML Meeting (skeleton from minutes)","general_area":""}],"minutes":[{"urn":"urn:oiml:ciml:minutes:ciml-7-fra","language_code":"fra"}]},{"source_file":"ciml-8-resolutions","source_title":"8th CIML Meeting (skeleton from minutes)","meeting_date":"","venue":"","city":"","country_code":"","year":"","body_type":"ciml","language":"fr","doi":"","resolution_count":0,"urn":"urn:oiml:ciml:meeting:ciml-8","virtual":false,"committee":"","localizations":[{"language_code":"fra","script":"Latn","title":"8th CIML Meeting (skeleton from minutes)","general_area":""}],"minutes":[{"urn":"urn:oiml:ciml:minutes:ciml-8-fra","language_code":"fra"}]},{"source_file":"ciml-9-resolutions","source_title":"9th CIML Meeting (skeleton from minutes)","meeting_date":"","venue":"","city":"","country_code":"","year":"","body_type":"ciml","language":"fr","doi":"","resolution_count":0,"urn":"urn:oiml:ciml:meeting:ciml-9","virtual":false,"committee":"","localizations":[{"language_code":"fra","script":"Latn","title":"9th CIML Meeting (skeleton from minutes)","general_area":""}],"minutes":[{"urn":"urn:oiml:ciml:minutes:ciml-9-fra","language_code":"fra"}]},{"source_file":"conference-12-resolutions","source_title":"12th OIML Conference — Joint CIML-39 + DC Decisions (EN)","meeting_date":"","venue":"Berlin, Germany","city":"","country_code":"","year":"","body_type":"conference","language":"en","doi":"","resolution_count":0,"urn":"urn:oiml:conference:meeting:conference-12","virtual":false,"committee":"International Conference of Legal Metrology","localizations":[{"language_code":"eng","script":"Latn","title":"12th OIML Conference — Joint CIML-39 + DC Decisions (EN)","general_area":"Berlin, Germany"},{"language_code":"fra","script":"Latn","title":"12e Conférence OIML — Décisions (FR)","general_area":"Berlin, Germany"}],"minutes":[]},{"source_file":"conference-13-resolutions","source_title":"13th OIML Conference — Resolutions (EN/FR)","meeting_date":"","venue":"Sydney, Australia","city":"","country_code":"","year":"","body_type":"conference","language":"en","doi":"","resolution_count":0,"urn":"urn:oiml:conference:meeting:conference-13","virtual":false,"committee":"International Conference of Legal Metrology","localizations":[{"language_code":"eng","script":"Latn","title":"13th OIML Conference — Resolutions (EN/FR)","general_area":"Sydney, Australia"},{"language_code":"fra","script":"Latn","title":"13th OIML Conference — Resolutions (EN/FR)","general_area":"Sydney, Australia"}],"minutes":[]},{"source_file":"conference-14-resolutions","source_title":"14th OIML Conference — Resolutions (EN)","meeting_date":"","venue":"Bucharest, Romania","city":"","country_code":"","year":"","body_type":"conference","language":"en","doi":"","resolution_count":0,"urn":"urn:oiml:conference:meeting:conference-14","virtual":false,"committee":"International Conference of Legal Metrology","localizations":[{"language_code":"eng","script":"Latn","title":"14th OIML Conference — Resolutions (EN)","general_area":"Bucharest, Romania"},{"language_code":"fra","script":"Latn","title":"14e Conférence OIML — Résolutions (FR)","general_area":"Bucharest, Romania"}],"minutes":[]},{"source_file":"conference-15-resolutions","source_title":"15th OIML Conference — Resolutions (EN)","meeting_date":"","venue":"Strasbourg, France","city":"","country_code":"","year":"","body_type":"conference","language":"en","doi":"","resolution_count":0,"urn":"urn:oiml:conference:meeting:conference-15","virtual":false,"committee":"International Conference of Legal Metrology","localizations":[{"language_code":"eng","script":"Latn","title":"15th OIML Conference — Resolutions (EN)","general_area":"Strasbourg, France"},{"language_code":"fra","script":"Latn","title":"15e Conférence OIML — Résolutions (FR)","general_area":"Strasbourg, France"}],"minutes":[]},{"source_file":"conference-16-resolutions","source_title":"16th OIML Conference — Resolutions (EN)","meeting_date":"","venue":"Online meeting","city":"","country_code":"","year":"","body_type":"conference","language":"en","doi":"","resolution_count":0,"urn":"urn:oiml:conference:meeting:conference-16","virtual":true,"committee":"International Conference of Legal Metrology","localizations":[{"language_code":"eng","script":"Latn","title":"16th OIML Conference — Resolutions (EN)","general_area":"Online meeting"},{"language_code":"fra","script":"Latn","title":"16e Conférence OIML — Résolutions (FR)","general_area":"Online meeting"}],"minutes":[]},{"source_file":"conference-17-resolutions","source_title":"17th OIML Conference — Resolutions (EN)","meeting_date":"","venue":"Paris, France","city":"","country_code":"","year":"","body_type":"conference","language":"en","doi":"","resolution_count":0,"urn":"urn:oiml:conference:meeting:conference-17","virtual":false,"committee":"International Conference of Legal Metrology","localizations":[{"language_code":"eng","script":"Latn","title":"17th OIML Conference — Resolutions (EN)","general_area":"Paris, France"}],"minutes":[]}]